textbase/__init__.py
textbase/bot.py
textbase/datatypes.py
textbase/helpers.py
textbase/message.py
textbase/models.py
textbase/template/main.py
textbase/template/requirements.txt
textbase/textbase_cli.py
textbase/utils/download_build.py
textbase/utils/logs.py
textbase/utils/server.py
textbase_client-0.1.8.dist-info/METADATA
textbase_client-0.1.8.dist-info/WHEEL
textbase_client-0.1.8.dist-info/entry_points.txt
textbase_client-0.1.8.dist-info/RECORD
