Metadata-Version: 2.1
Name: textbase-client
Version: 0.1.8
Summary: A python library to help you create chatbots easily with some more configurations
Author: kaus-cofactory
Author-email: kaustubhshukla@cofactory.ai
Requires-Python: >=3.9.0,<4.0.0
Classifier: Programming Language :: Python :: 3
Classifier: Programming Language :: Python :: 3.9
Classifier: Programming Language :: Python :: 3.10
Classifier: Programming Language :: Python :: 3.11
Requires-Dist: functions-framework (>=3.4.0,<4.0.0)
Requires-Dist: google-generativeai (>=0.1.0,<0.2.0)
Requires-Dist: openai (>=1.1.2,<2.0.0)
Requires-Dist: pillow (>=10.0.1,<11.0.0)
Requires-Dist: pydantic (>=2.3.0,<3.0.0)
Requires-Dist: python-dotenv (>=1.0.0,<2.0.0)
Requires-Dist: requests (>=2.31.0,<3.0.0)
Requires-Dist: rich (>=13.5.2,<14.0.0)
Requires-Dist: tabulate (>=0.9.0,<0.10.0)
Requires-Dist: yaspin (>=3.0.0,<4.0.0)
